appsync_router/__init__.py
appsync_router/context.py
appsync_router/exceptions.py
appsync_router/matches.py
appsync_router/routes.py
appsync_router-4.0.3.dist-info/LICENSE
appsync_router-4.0.3.dist-info/METADATA
appsync_router-4.0.3.dist-info/WHEEL
appsync_router-4.0.3.dist-info/top_level.txt
appsync_router-4.0.3.dist-info/RECORD
