Metadata-Version: 2.1
Name: appsync-router
Version: 4.0.3
Summary: A framework easily routing AppSync requests using AWS Lambda
Home-page: https://github.com/QuiNovas/appsync-router
Author: Joseph Wortmann
Author-email: jwortmann@quinovas.com
License: Apache 2.0
Keywords: appsync,lambda
Platform: UNKNOWN
Classifier: Development Status :: 4 - Beta
Classifier: Intended Audience :: Developers
Classifier: License :: OSI Approved :: Apache Software License
Classifier: Programming Language :: Python :: 3.8
Requires-Python: >=3.9
License-File: LICENSE
Requires-Dist: multipledispatch
